minaibot/__init__.py
minaibot/__pycache__/__init__.cpython-311.pyc
minaibot/answers/__init__.py
minaibot/answers/start.py
minaibot/answers/__pycache__/__init__.cpython-311.pyc
minaibot/answers/__pycache__/start.cpython-311.pyc
minaibot/bot/__init__.py
minaibot/bot/config.py
minaibot/bot/myserver.py
minaibot/bot/routes.py
minaibot/bot/__pycache__/__init__.cpython-311.pyc
minaibot/bot/__pycache__/config.cpython-311.pyc
minaibot/bot/__pycache__/routes.cpython-311.pyc
minaibot/core/__init__.py
minaibot/core/decorators.py
minaibot/core/router.py
minaibot/core/run.py
minaibot/core/server.py
minaibot/core/__pycache__/__init__.cpython-311.pyc
minaibot/core/__pycache__/decorators.cpython-311.pyc
minaibot/core/__pycache__/router.cpython-311.pyc
minaibot/core/__pycache__/run.cpython-311.pyc
minaibot/core/__pycache__/server.cpython-311.pyc
minaibot-0.1.2.dist-info/LICENSE
minaibot-0.1.2.dist-info/METADATA
minaibot-0.1.2.dist-info/WHEEL
minaibot-0.1.2.dist-info/entry_points.txt
minaibot-0.1.2.dist-info/top_level.txt
minaibot-0.1.2.dist-info/RECORD
