Metadata-Version: 2.1
Name: minaibot
Version: 0.1.2
Summary: BotFramework
Home-page: https://github.com/nikita-minai/minaibot
Author: Nikita Minai
Author-email: nikita.minai@ya.ru
Classifier: Programming Language :: Python :: 3
Classifier: License :: OSI Approved :: MIT License
Classifier: Operating System :: OS Independent
Requires-Python: >=3.6
License-File: LICENSE
Requires-Dist: requests
Requires-Dist: pyTelegramBotAPI
Requires-Dist: telebot
